ape_pie/__init__.py
ape_pie/client.py
ape_pie/exceptions.py
ape_pie/py.typed
ape_pie/typing.py
ape_pie-0.2.0.dist-info/LICENSE
ape_pie-0.2.0.dist-info/METADATA
ape_pie-0.2.0.dist-info/WHEEL
ape_pie-0.2.0.dist-info/top_level.txt
ape_pie-0.2.0.dist-info/RECORD
