Metadata-Version: 2.1
Name: ape-pie
Version: 0.2.0
Summary: A small API client abstraction layer on top of requests.
Author-email: Maykin Media <support@maykinmedia.nl>, Sergei Maertens <sergei@maykinmedia.nl>
Project-URL: Documentation, http://ape-pie.readthedocs.io/en/latest/
Project-URL: Changelog, https://github.com/maykinmedia/ape-pie/blob/main/CHANGELOG.rst
Project-URL: Bug Tracker, https://github.com/maykinmedia/ape-pie/issues
Project-URL: Source Code, https://github.com/maykinmedia/ape-pie
Keywords: api client,requests
Classifier: Development Status :: 5 - Production/Stable
Classifier: Intended Audience :: Developers
Classifier: Programming Language :: Python :: 3
Classifier: Programming Language :: Python :: 3.10
Classifier: Programming Language :: Python :: 3.11
Classifier: License :: OSI Approved :: MIT License
Classifier: Operating System :: OS Independent
Classifier: Topic :: Software Development :: Libraries :: Python Modules
Requires-Python: >=3.9
License-File: LICENSE
Requires-Dist: furl
Requires-Dist: requests
Provides-Extra: dev
Requires-Dist: pytest ; extra == 'dev'
Requires-Dist: pytest-cov ; extra == 'dev'
Requires-Dist: hypothesis ; extra == 'dev'
Requires-Dist: requests-mock ; extra == 'dev'
Requires-Dist: tox ; extra == 'dev'
Requires-Dist: isort ; extra == 'dev'
Requires-Dist: black ; extra == 'dev'
Requires-Dist: flake8 ; extra == 'dev'
Requires-Dist: tbump ; extra == 'dev'
Requires-Dist: tomli ; (python_version < "3.11") and extra == 'dev'
Provides-Extra: docs
Requires-Dist: sphinx ; extra == 'docs'
Requires-Dist: sphinx-rtd-theme ; extra == 'docs'
Provides-Extra: types
Requires-Dist: mypy ; extra == 'types'
Requires-Dist: types-requests ; extra == 'types'
Requires-Dist: typing-extensions ; extra == 'types'
